src/__init__.py
src/imgur_dl.py
src/source/__init__.py
src/source/download.py
src/source/globfuncs.py
src/source/loadimage.py
imgur_dl-0.3.2.dist-info/LICENSE
imgur_dl-0.3.2.dist-info/METADATA
imgur_dl-0.3.2.dist-info/WHEEL
imgur_dl-0.3.2.dist-info/entry_points.txt
imgur_dl-0.3.2.dist-info/top_level.txt
imgur_dl-0.3.2.dist-info/RECORD
