Metadata-Version: 2.1
Name: imgur-dl
Version: 0.3.2
Summary: Imgur downloader
Home-page: https://github.com/feimaomiao/imgur-dl
Author: Matthew Lam
Author-email: lcpmatthew@gmail.com
License: UNKNOWN
Keywords: imgur photo video download
Platform: UNKNOWN
Classifier: Programming Language :: Python :: 3.6
Classifier: Programming Language :: Python :: 3.7
Classifier: Programming Language :: Python :: 3.8
Classifier: Natural Language :: English
Classifier: License :: OSI Approved :: MIT License
Classifier: Intended Audience :: Developers
Classifier: Operating System :: OS Independent
Classifier: Topic :: Internet
Requires-Python: >=3.6
Requires-Dist: lazyloads
Requires-Dist: tqdm
Requires-Dist: requests
Requires-Dist: pillow
